infretis/__init__.py
infretis/asyncrunner.py
infretis/bin.py
infretis/classes/__init__.py
infretis/classes/engines/__init__.py
infretis/classes/engines/ams.py
infretis/classes/engines/ase_engine.py
infretis/classes/engines/cp2k.py
infretis/classes/engines/enginebase.py
infretis/classes/engines/engineparts.py
infretis/classes/engines/factory.py
infretis/classes/engines/gromacs.py
infretis/classes/engines/lammps.py
infretis/classes/engines/turtlemdengine.py
infretis/classes/formatter.py
infretis/classes/orderparameter.py
infretis/classes/path.py
infretis/classes/repex.py
infretis/classes/system.py
infretis/core/__init__.py
infretis/core/core.py
infretis/core/tis.py
infretis/scheduler.py
infretis/setup.py
infretis/tools/__init__.py
infretis/tools/generate_H2_loadpaths.py
infretis-2025.4.dist-info/LICENSE
infretis-2025.4.dist-info/METADATA
infretis-2025.4.dist-info/WHEEL
infretis-2025.4.dist-info/entry_points.txt
infretis-2025.4.dist-info/RECORD
