Metadata-Version: 2.3
Name: infretis
Version: 2025.4
Summary: Infinite swapping parallel RETIS
License: MIT
Author: Daniel Zhang
Author-email: daniel.t.zhang@ntnu.no
Requires-Python: >=3.8.12,<3.14
Classifier: License :: OSI Approved :: MIT License
Classifier: Programming Language :: Python :: 3
Classifier: Programming Language :: Python :: 3.9
Classifier: Programming Language :: Python :: 3.10
Classifier: Programming Language :: Python :: 3.11
Classifier: Programming Language :: Python :: 3.12
Classifier: Programming Language :: Python :: 3.13
Requires-Dist: ase (>=3.20.0,<4.0.0)
Requires-Dist: numpy (>=1.21.2,<2.0.0)
Requires-Dist: tomli (>=2.0.1,<3.0.0)
Requires-Dist: tomli-w (>=1.0.0,<2.0.0)
